{
  "version": "7",
  "dialect": "postgresql",
  "entries": [
    {
      "idx": 0,
      "version": "7",
      "when": 1774172948023,
      "tag": "0000_hard_nightcrawler",
      "breakpoints": true
    },
    {
      "idx": 1,
      "version": "7",
      "when": 1742601600000,
      "tag": "0001_system_tables",
      "breakpoints": true
    },
    {
      "idx": 2,
      "version": "7",
      "when": 1774188756865,
      "tag": "0002_steep_black_tom",
      "breakpoints": true
    },
    {
      "idx": 3,
      "version": "7",
      "when": 1774230164669,
      "tag": "0003_lazy_deathstrike",
      "breakpoints": true
    },
    {
      "idx": 4,
      "version": "7",
      "when": 1774232385136,
      "tag": "0004_boring_old_lace",
      "breakpoints": true
    },
    {
      "idx": 5,
      "version": "7",
      "when": 1774240344516,
      "tag": "0005_dry_inertia",
      "breakpoints": true
    },
    {
      "idx": 6,
      "version": "7",
      "when": 1774244421470,
      "tag": "0006_solid_anita_blake",
      "breakpoints": true
    },
    {
      "idx": 7,
      "version": "7",
      "when": 1774253291499,
      "tag": "0007_supreme_prodigy",
      "breakpoints": true
    },
    {
      "idx": 8,
      "version": "7",
      "when": 1774256480327,
      "tag": "0008_omniscient_gladiator",
      "breakpoints": true
    },
    {
      "idx": 9,
      "version": "7",
      "when": 1774257873449,
      "tag": "0009_condemned_living_lightning",
      "breakpoints": true
    },
    {
      "idx": 10,
      "version": "7",
      "when": 1774258014412,
      "tag": "0010_lowly_jasper_sitwell",
      "breakpoints": true
    },
    {
      "idx": 11,
      "version": "7",
      "when": 1774283176021,
      "tag": "0011_burly_skaar",
      "breakpoints": true
    },
    {
      "idx": 12,
      "version": "7",
      "when": 1774323057284,
      "tag": "0012_worried_gressill",
      "breakpoints": true
    },
    {
      "idx": 13,
      "version": "7",
      "when": 1774332295714,
      "tag": "0013_cheerful_shockwave",
      "breakpoints": true
    },
    {
      "idx": 14,
      "version": "7",
      "when": 1774400149542,
      "tag": "0014_outgoing_namora",
      "breakpoints": true
    },
    {
      "idx": 15,
      "version": "7",
      "when": 1774422572217,
      "tag": "0015_cynical_colleen_wing",
      "breakpoints": true
    },
    {
      "idx": 16,
      "version": "7",
      "when": 1774442280579,
      "tag": "0016_abnormal_celestials",
      "breakpoints": true
    },
    {
      "idx": 17,
      "version": "7",
      "when": 1774448947252,
      "tag": "0017_ambiguous_mister_sinister",
      "breakpoints": true
    },
    {
      "idx": 18,
      "version": "7",
      "when": 1774449388450,
      "tag": "0018_fancy_garia",
      "breakpoints": true
    },
    {
      "idx": 19,
      "version": "7",
      "when": 1774500000000,
      "tag": "0019_email_configs",
      "breakpoints": true
    },
    {
      "idx": 20,
      "version": "7",
      "when": 1774515715313,
      "tag": "0020_colossal_hercules",
      "breakpoints": true
    },
    {
      "idx": 21,
      "version": "7",
      "when": 1774517721030,
      "tag": "0021_goofy_anthem",
      "breakpoints": true
    },
    {
      "idx": 22,
      "version": "7",
      "when": 1774536385806,
      "tag": "0022_minor_slayback",
      "breakpoints": true
    },
    {
      "idx": 23,
      "version": "7",
      "when": 1774620000000,
      "tag": "0023_user_api_tokens",
      "breakpoints": true
    },
    {
      "idx": 24,
      "version": "7",
      "when": 1774596626394,
      "tag": "0024_secret_bruce_banner",
      "breakpoints": true
    },
    {
      "idx": 25,
      "version": "7",
      "when": 1774598529370,
      "tag": "0025_shallow_maddog",
      "breakpoints": true
    },
    {
      "idx": 26,
      "version": "7",
      "when": 1774695990053,
      "tag": "0026_little_wallflower",
      "breakpoints": true
    },
    {
      "idx": 27,
      "version": "7",
      "when": 1774779975212,
      "tag": "0027_loud_norrin_radd",
      "breakpoints": true
    },
    {
      "idx": 28,
      "version": "7",
      "when": 1775001600000,
      "tag": "0028_s3_cos_storage",
      "breakpoints": true
    },
    {
      "idx": 29,
      "version": "7",
      "when": 1775001600001,
      "tag": "0029_cuddly_havok",
      "breakpoints": true
    },
    {
      "idx": 30,
      "version": "7",
      "when": 1775001600002,
      "tag": "0030_odd_bromley",
      "breakpoints": true
    },
    {
      "idx": 31,
      "version": "7",
      "when": 1775019557134,
      "tag": "0031_talented_gertrude_yorkes",
      "breakpoints": true
    },
    {
      "idx": 32,
      "version": "7",
      "when": 1776686833219,
      "tag": "0032_young_nocturne",
      "breakpoints": true
    },
    {
      "idx": 33,
      "version": "7",
      "when": 1776695618887,
      "tag": "0033_foamy_venus",
      "breakpoints": true
    },
    {
      "idx": 34,
      "version": "7",
      "when": 1776782536795,
      "tag": "0034_gorgeous_mimic",
      "breakpoints": true
    },
    {
      "idx": 35,
      "version": "7",
      "when": 1777176934872,
      "tag": "0035_old_ares",
      "breakpoints": true
    },
    {
      "idx": 36,
      "version": "7",
      "when": 1777710943878,
      "tag": "0036_regular_nightshade",
      "breakpoints": true
    },
    {
      "idx": 37,
      "version": "7",
      "when": 1777731579945,
      "tag": "0037_giant_spitfire",
      "breakpoints": true
    },
    {
      "idx": 38,
      "version": "7",
      "when": 1777792907590,
      "tag": "0038_glamorous_leader",
      "breakpoints": true
    },
    {
      "idx": 39,
      "version": "7",
      "when": 1778035019203,
      "tag": "0039_sloppy_ender_wiggin",
      "breakpoints": true
    },
    {
      "idx": 40,
      "version": "7",
      "when": 1778042611766,
      "tag": "0040_robust_bloodstorm",
      "breakpoints": true
    },
    {
      "idx": 41,
      "version": "7",
      "when": 1778142638960,
      "tag": "0041_grey_mandarin",
      "breakpoints": true
    },
    {
      "idx": 42,
      "version": "7",
      "when": 1778294885533,
      "tag": "0042_magical_diamondback",
      "breakpoints": true
    },
    {
      "idx": 43,
      "version": "7",
      "when": 1778403599407,
      "tag": "0043_watery_bushwacker",
      "breakpoints": true
    },
    {
      "idx": 44,
      "version": "7",
      "when": 1779020046057,
      "tag": "0044_crazy_omega_red",
      "breakpoints": true
    },
    {
      "idx": 45,
      "version": "7",
      "when": 1779031787754,
      "tag": "0045_sour_ben_urich",
      "breakpoints": true
    },
    {
      "idx": 46,
      "version": "7",
      "when": 1779196263005,
      "tag": "0046_useful_mastermind",
      "breakpoints": true
    },
    {
      "idx": 47,
      "version": "7",
      "when": 1779281383848,
      "tag": "0047_remarkable_blockbuster",
      "breakpoints": true
    },
    {
      "idx": 48,
      "version": "7",
      "when": 1779284207561,
      "tag": "0048_careful_norrin_radd",
      "breakpoints": true
    },
    {
      "idx": 49,
      "version": "7",
      "when": 1779370607561,
      "tag": "0049_drop_legacy_message_template_menus",
      "breakpoints": true
    },
    {
      "idx": 50,
      "version": "7",
      "when": 1779292461061,
      "tag": "0050_zippy_hex",
      "breakpoints": true
    },
    {
      "idx": 51,
      "version": "7",
      "when": 1779400000000,
      "tag": "0051_rename_notices_to_announcements",
      "breakpoints": true
    },
    {
      "idx": 52,
      "version": "7",
      "when": 1779373951239,
      "tag": "0052_jazzy_strong_guy",
      "breakpoints": true
    },
    {
      "idx": 53,
      "version": "7",
      "when": 1779580800000,
      "tag": "0053_table_comments",
      "breakpoints": true
    },
    {
      "idx": 54,
      "version": "7",
      "when": 1779664000000,
      "tag": "0054_great_norrin_radd",
      "breakpoints": true
    },
    {
      "idx": 55,
      "version": "7",
      "when": 1779664100000,
      "tag": "0055_little_susan_delgado",
      "breakpoints": true
    },
    {
      "idx": 56,
      "version": "7",
      "when": 1779664200000,
      "tag": "0056_wandering_thunderbird",
      "breakpoints": true
    },
    {
      "idx": 57,
      "version": "7",
      "when": 1779664300000,
      "tag": "0057_workflow_node_types",
      "breakpoints": true
    },
    {
      "idx": 58,
      "version": "7",
      "when": 1779664400000,
      "tag": "0058_secret_maggott",
      "breakpoints": true
    },
    {
      "idx": 59,
      "version": "7",
      "when": 1779664400001,
      "tag": "0059_massive_marrow",
      "breakpoints": true
    },
    {
      "idx": 60,
      "version": "7",
      "when": 1779664400002,
      "tag": "0060_worried_gargoyle",
      "breakpoints": true
    },
    {
      "idx": 61,
      "version": "7",
      "when": 1779664401002,
      "tag": "0061_empty_madame_masque",
      "breakpoints": true
    },
    {
      "idx": 62,
      "version": "7",
      "when": 1779664402000,
      "tag": "0062_wet_magma",
      "breakpoints": true
    },
    {
      "idx": 63,
      "version": "7",
      "when": 1779664403000,
      "tag": "0063_elite_thanos",
      "breakpoints": true
    },
    {
      "idx": 64,
      "version": "7",
      "when": 1779720709869,
      "tag": "0064_mixed_inertia",
      "breakpoints": true
    },
    {
      "idx": 65,
      "version": "7",
      "when": 1779722171512,
      "tag": "0065_large_rocket_raccoon",
      "breakpoints": true
    },
    {
      "idx": 66,
      "version": "7",
      "when": 1779769299127,
      "tag": "0066_burly_eternity",
      "breakpoints": true
    },
    {
      "idx": 67,
      "version": "7",
      "when": 1779770377312,
      "tag": "0067_clumsy_sunspot",
      "breakpoints": true
    },
    {
      "idx": 68,
      "version": "7",
      "when": 1779780834220,
      "tag": "0068_lovely_lifeguard",
      "breakpoints": true
    },
    {
      "idx": 69,
      "version": "7",
      "when": 1779782425871,
      "tag": "0069_true_komodo",
      "breakpoints": true
    },
    {
      "idx": 70,
      "version": "7",
      "when": 1779788908060,
      "tag": "0070_futuristic_maggott",
      "breakpoints": true
    },
    {
      "idx": 71,
      "version": "7",
      "when": 1779790081783,
      "tag": "0071_jazzy_gabe_jones",
      "breakpoints": true
    },
    {
      "idx": 72,
      "version": "7",
      "when": 1779896196416,
      "tag": "0072_illegal_reptil",
      "breakpoints": true
    },
    {
      "idx": 73,
      "version": "7",
      "when": 1779975182728,
      "tag": "0073_youthful_butterfly",
      "breakpoints": true
    },
    {
      "idx": 74,
      "version": "7",
      "when": 1779980440820,
      "tag": "0074_useful_dakota_north",
      "breakpoints": true
    },
    {
      "idx": 75,
      "version": "7",
      "when": 1779981592110,
      "tag": "0075_peaceful_bulldozer",
      "breakpoints": true
    },
    {
      "idx": 76,
      "version": "7",
      "when": 1779984175779,
      "tag": "0076_last_shockwave",
      "breakpoints": true
    },
    {
      "idx": 77,
      "version": "7",
      "when": 1780053641930,
      "tag": "0077_brief_morph",
      "breakpoints": true
    },
    {
      "idx": 78,
      "version": "7",
      "when": 1780060832627,
      "tag": "0078_old_mojo",
      "breakpoints": true
    },
    {
      "idx": 79,
      "version": "7",
      "when": 1780132303099,
      "tag": "0079_ancient_norman_osborn",
      "breakpoints": true
    },
    {
      "idx": 80,
      "version": "7",
      "when": 1780138038603,
      "tag": "0080_slippery_calypso",
      "breakpoints": true
    },
    {
      "idx": 81,
      "version": "7",
      "when": 1780140764518,
      "tag": "0081_blue_stone_men",
      "breakpoints": true
    },
    {
      "idx": 82,
      "version": "7",
      "when": 1780197178386,
      "tag": "0082_dark_clint_barton",
      "breakpoints": true
    },
    {
      "idx": 83,
      "version": "7",
      "when": 1780217373354,
      "tag": "0083_solid_meggan",
      "breakpoints": true
    },
    {
      "idx": 84,
      "version": "7",
      "when": 1780300000000,
      "tag": "0084_scheduled_announcement",
      "breakpoints": true
    },
    {
      "idx": 85,
      "version": "7",
      "when": 1780373950892,
      "tag": "0085_curvy_kree",
      "breakpoints": true
    },
    {
      "idx": 86,
      "version": "7",
      "when": 1780410882527,
      "tag": "0086_wakeful_vin_gonzales",
      "breakpoints": true
    },
    {
      "idx": 87,
      "version": "7",
      "when": 1780641876526,
      "tag": "0087_clever_lyja",
      "breakpoints": true
    },
    {
      "idx": 88,
      "version": "7",
      "when": 1780701618692,
      "tag": "0088_burly_virginia_dare",
      "breakpoints": true
    },
    {
      "idx": 89,
      "version": "7",
      "when": 1780707387418,
      "tag": "0089_thin_wallflower",
      "breakpoints": true
    },
    {
      "idx": 90,
      "version": "7",
      "when": 1780712618241,
      "tag": "0090_wet_captain_america",
      "breakpoints": true
    },
    {
      "idx": 91,
      "version": "7",
      "when": 1780727015336,
      "tag": "0091_glamorous_joshua_kane",
      "breakpoints": true
    },
    {
      "idx": 92,
      "version": "7",
      "when": 1780746302000,
      "tag": "0092_chilly_ultimates",
      "breakpoints": true
    },
    {
      "idx": 93,
      "version": "7",
      "when": 1780802795128,
      "tag": "0093_kind_santa_claus",
      "breakpoints": true
    },
    {
      "idx": 94,
      "version": "7",
      "when": 1780823411366,
      "tag": "0094_fuzzy_purple_man",
      "breakpoints": true
    },
    {
      "idx": 95,
      "version": "7",
      "when": 1780992574005,
      "tag": "0095_harsh_king_cobra",
      "breakpoints": true
    },
    {
      "idx": 96,
      "version": "7",
      "when": 1781012944098,
      "tag": "0096_gorgeous_ghost_rider",
      "breakpoints": true
    },
    {
      "idx": 97,
      "version": "7",
      "when": 1781077591241,
      "tag": "0097_sad_argent",
      "breakpoints": true
    },
    {
      "idx": 98,
      "version": "7",
      "when": 1781083140937,
      "tag": "0098_lush_la_nuit",
      "breakpoints": true
    },
    {
      "idx": 99,
      "version": "7",
      "when": 1781250812447,
      "tag": "0099_sudden_anthem",
      "breakpoints": true
    },
    {
      "idx": 100,
      "version": "7",
      "when": 1781273941227,
      "tag": "0100_fluffy_the_liberteens",
      "breakpoints": true
    },
    {
      "idx": 101,
      "version": "7",
      "when": 1781357343592,
      "tag": "0101_overconfident_blur",
      "breakpoints": true
    },
    {
      "idx": 102,
      "version": "7",
      "when": 1781369115537,
      "tag": "0102_lame_newton_destine",
      "breakpoints": true
    },
    {
      "idx": 103,
      "version": "7",
      "when": 1781402112935,
      "tag": "0103_slimy_harpoon",
      "breakpoints": true
    },
    {
      "idx": 104,
      "version": "7",
      "when": 1781532363396,
      "tag": "0104_flaky_dark_phoenix",
      "breakpoints": true
    },
    {
      "idx": 105,
      "version": "7",
      "when": 1781614731623,
      "tag": "0105_groovy_paper_doll",
      "breakpoints": true
    },
    {
      "idx": 106,
      "version": "7",
      "when": 1781622861077,
      "tag": "0106_cute_proudstar",
      "breakpoints": true
    },
    {
      "idx": 107,
      "version": "7",
      "when": 1781706635535,
      "tag": "0107_aberrant_matthew_murdock",
      "breakpoints": true
    },
    {
      "idx": 108,
      "version": "7",
      "when": 1781712609234,
      "tag": "0108_sleepy_lenny_balinger",
      "breakpoints": true
    },
    {
      "idx": 109,
      "version": "7",
      "when": 1781813971708,
      "tag": "0109_natural_charles_xavier",
      "breakpoints": true
    },
    {
      "idx": 110,
      "version": "7",
      "when": 1781813993601,
      "tag": "0110_remarkable_skullbuster",
      "breakpoints": true
    },
    {
      "idx": 111,
      "version": "7",
      "when": 1781876071154,
      "tag": "0111_same_vin_gonzales",
      "breakpoints": true
    },
    {
      "idx": 112,
      "version": "7",
      "when": 1781878326680,
      "tag": "0112_soft_queen_noir",
      "breakpoints": true
    },
    {
      "idx": 113,
      "version": "7",
      "when": 1781880885531,
      "tag": "0113_opposite_lucky_pierre",
      "breakpoints": true
    },
    {
      "idx": 114,
      "version": "7",
      "when": 1781884623039,
      "tag": "0114_living_green_goblin",
      "breakpoints": true
    },
    {
      "idx": 115,
      "version": "7",
      "when": 1781888053238,
      "tag": "0115_shallow_kid_colt",
      "breakpoints": true
    },
    {
      "idx": 116,
      "version": "7",
      "when": 1781888074736,
      "tag": "0116_bouncy_captain_cross",
      "breakpoints": true
    },
    {
      "idx": 117,
      "version": "7",
      "when": 1781902296606,
      "tag": "0117_ambiguous_luminals",
      "breakpoints": true
    },
    {
      "idx": 118,
      "version": "7",
      "when": 1781903422908,
      "tag": "0118_fearless_paladin",
      "breakpoints": true
    },
    {
      "idx": 119,
      "version": "7",
      "when": 1781914783999,
      "tag": "0119_special_landau",
      "breakpoints": true
    },
    {
      "idx": 120,
      "version": "7",
      "when": 1781916602755,
      "tag": "0120_fat_spirit",
      "breakpoints": true
    },
    {
      "idx": 121,
      "version": "7",
      "when": 1781917269162,
      "tag": "0121_fine_slayback",
      "breakpoints": true
    },
    {
      "idx": 122,
      "version": "7",
      "when": 1781920167594,
      "tag": "0122_amusing_prodigy",
      "breakpoints": true
    },
    {
      "idx": 123,
      "version": "7",
      "when": 1781945496166,
      "tag": "0123_opposite_spiral",
      "breakpoints": true
    },
    {
      "idx": 124,
      "version": "7",
      "when": 1781947894641,
      "tag": "0124_sloppy_james_howlett",
      "breakpoints": true
    },
    {
      "idx": 125,
      "version": "7",
      "when": 1781961426866,
      "tag": "0125_jazzy_amphibian",
      "breakpoints": true
    },
    {
      "idx": 126,
      "version": "7",
      "when": 1781966210816,
      "tag": "0126_wise_ender_wiggin",
      "breakpoints": true
    },
    {
      "idx": 127,
      "version": "7",
      "when": 1781968485807,
      "tag": "0127_stormy_sentry",
      "breakpoints": true
    },
    {
      "idx": 128,
      "version": "7",
      "when": 1781999157845,
      "tag": "0128_glamorous_outlaw_kid",
      "breakpoints": true
    },
    {
      "idx": 129,
      "version": "7",
      "when": 1782000547233,
      "tag": "0129_mature_dakota_north",
      "breakpoints": true
    },
    {
      "idx": 130,
      "version": "7",
      "when": 1782019295827,
      "tag": "0130_large_starhawk",
      "breakpoints": true
    },
    {
      "idx": 131,
      "version": "7",
      "when": 1782053137812,
      "tag": "0131_chubby_squirrel_girl",
      "breakpoints": true
    },
    {
      "idx": 132,
      "version": "7",
      "when": 1782098271941,
      "tag": "0132_cheerful_prism",
      "breakpoints": true
    },
    {
      "idx": 133,
      "version": "7",
      "when": 1782107338045,
      "tag": "0133_woozy_the_hood",
      "breakpoints": true
    },
    {
      "idx": 134,
      "version": "7",
      "when": 1782113995696,
      "tag": "0134_unusual_franklin_richards",
      "breakpoints": true
    },
    {
      "idx": 135,
      "version": "7",
      "when": 1782119231295,
      "tag": "0135_right_micromax",
      "breakpoints": true
    },
    {
      "idx": 136,
      "version": "7",
      "when": 1782128092768,
      "tag": "0136_normal_jasper_sitwell",
      "breakpoints": true
    },
    {
      "idx": 137,
      "version": "7",
      "when": 1782144565437,
      "tag": "0137_magenta_anthem",
      "breakpoints": true
    },
    {
      "idx": 138,
      "version": "7",
      "when": 1782192326670,
      "tag": "0138_daily_ezekiel",
      "breakpoints": true
    },
    {
      "idx": 139,
      "version": "7",
      "when": 1782208058348,
      "tag": "0139_fuzzy_machine_man",
      "breakpoints": true
    },
    {
      "idx": 140,
      "version": "7",
      "when": 1782223523118,
      "tag": "0140_nifty_winter_soldier",
      "breakpoints": true
    },
    {
      "idx": 141,
      "version": "7",
      "when": 1782229407082,
      "tag": "0141_abandoned_vulcan",
      "breakpoints": true
    },
    {
      "idx": 142,
      "version": "7",
      "when": 1782230932656,
      "tag": "0142_cuddly_morgan_stark",
      "breakpoints": true
    },
    {
      "idx": 143,
      "version": "7",
      "when": 1782232472819,
      "tag": "0143_little_serpent_society",
      "breakpoints": true
    },
    {
      "idx": 144,
      "version": "7",
      "when": 1782233660772,
      "tag": "0144_shocking_lionheart",
      "breakpoints": true
    },
    {
      "idx": 145,
      "version": "7",
      "when": 1782267824081,
      "tag": "0145_absurd_butterfly",
      "breakpoints": true
    },
    {
      "idx": 146,
      "version": "7",
      "when": 1782271825339,
      "tag": "0146_purge_legacy_bot",
      "breakpoints": true
    },
    {
      "idx": 147,
      "version": "7",
      "when": 1782274589998,
      "tag": "0147_hot_titania",
      "breakpoints": true
    },
    {
      "idx": 148,
      "version": "7",
      "when": 1782282026654,
      "tag": "0148_square_masque",
      "breakpoints": true
    },
    {
      "idx": 149,
      "version": "7",
      "when": 1782286443427,
      "tag": "0149_woozy_giant_girl",
      "breakpoints": true
    },
    {
      "idx": 150,
      "version": "7",
      "when": 1782288134921,
      "tag": "0150_abnormal_eddie_brock",
      "breakpoints": true
    },
    {
      "idx": 151,
      "version": "7",
      "when": 1782293230995,
      "tag": "0151_magical_azazel",
      "breakpoints": true
    },
    {
      "idx": 152,
      "version": "7",
      "when": 1782300407910,
      "tag": "0152_condemned_nebula",
      "breakpoints": true
    },
    {
      "idx": 153,
      "version": "7",
      "when": 1782301666047,
      "tag": "0153_naive_killraven",
      "breakpoints": true
    },
    {
      "idx": 154,
      "version": "7",
      "when": 1782303959571,
      "tag": "0154_numerous_mastermind",
      "breakpoints": true
    },
    {
      "idx": 155,
      "version": "7",
      "when": 1782306684517,
      "tag": "0155_purple_ironclad",
      "breakpoints": true
    },
    {
      "idx": 156,
      "version": "7",
      "when": 1782307527002,
      "tag": "0156_flippant_doctor_faustus",
      "breakpoints": true
    },
    {
      "idx": 157,
      "version": "7",
      "when": 1782308146124,
      "tag": "0157_secret_black_knight",
      "breakpoints": true
    },
    {
      "idx": 158,
      "version": "7",
      "when": 1782309901294,
      "tag": "0158_sparkling_iron_patriot",
      "breakpoints": true
    },
    {
      "idx": 159,
      "version": "7",
      "when": 1782312408870,
      "tag": "0159_shiny_power_man",
      "breakpoints": true
    },
    {
      "idx": 160,
      "version": "7",
      "when": 1782315024053,
      "tag": "0160_slimy_mockingbird",
      "breakpoints": true
    },
    {
      "idx": 161,
      "version": "7",
      "when": 1782315842776,
      "tag": "0161_empty_nico_minoru",
      "breakpoints": true
    },
    {
      "idx": 162,
      "version": "7",
      "when": 1782350499123,
      "tag": "0162_careful_warbird",
      "breakpoints": true
    },
    {
      "idx": 163,
      "version": "7",
      "when": 1782351622677,
      "tag": "0163_worried_mysterio",
      "breakpoints": true
    },
    {
      "idx": 164,
      "version": "7",
      "when": 1782360565787,
      "tag": "0164_fearless_kingpin",
      "breakpoints": true
    },
    {
      "idx": 165,
      "version": "7",
      "when": 1782371182518,
      "tag": "0165_smooth_sphinx",
      "breakpoints": true
    },
    {
      "idx": 166,
      "version": "7",
      "when": 1782473624499,
      "tag": "0166_green_ser_duncan",
      "breakpoints": true
    },
    {
      "idx": 167,
      "version": "7",
      "when": 1782483159306,
      "tag": "0167_broad_nova",
      "breakpoints": true
    },
    {
      "idx": 168,
      "version": "7",
      "when": 1782486657181,
      "tag": "0168_noisy_amazoness",
      "breakpoints": true
    },
    {
      "idx": 169,
      "version": "7",
      "when": 1782490212155,
      "tag": "0169_quiet_manta",
      "breakpoints": true
    },
    {
      "idx": 170,
      "version": "7",
      "when": 1782503806130,
      "tag": "0170_dry_maestro",
      "breakpoints": true
    },
    {
      "idx": 171,
      "version": "7",
      "when": 1782506099125,
      "tag": "0171_vengeful_pyro",
      "breakpoints": true
    },
    {
      "idx": 172,
      "version": "7",
      "when": 1782506483321,
      "tag": "0172_windy_gwen_stacy",
      "breakpoints": true
    },
    {
      "idx": 173,
      "version": "7",
      "when": 1782521657663,
      "tag": "0173_amazing_justice",
      "breakpoints": true
    },
    {
      "idx": 174,
      "version": "7",
      "when": 1782521984511,
      "tag": "0174_damp_carnage",
      "breakpoints": true
    },
    {
      "idx": 175,
      "version": "7",
      "when": 1782523915811,
      "tag": "0175_long_alice",
      "breakpoints": true
    }
  ]
}